tapir_archicad_mcp/__init__.py
tapir_archicad_mcp/app.py
tapir_archicad_mcp/context.py
tapir_archicad_mcp/logging_config.py
tapir_archicad_mcp/pagination.py
tapir_archicad_mcp/server.py
tapir_archicad_mcp/tools/__init__.py
tapir_archicad_mcp/tools/registration.py
tapir_archicad_mcp/tools/search_index.py
tapir_archicad_mcp/tools/tool_registry.py
tapir_archicad_mcp/tools/custom/__init__.py
tapir_archicad_mcp/tools/custom/functions.py
tapir_archicad_mcp/tools/custom/models.py
tapir_archicad_mcp/tools/generated/__init__.py
tapir_archicad_mcp/tools/generated/official/__init__.py
tapir_archicad_mcp/tools/generated/official/addon_commands.py
tapir_archicad_mcp/tools/generated/official/attribute_commands.py
tapir_archicad_mcp/tools/generated/official/classification_commands.py
tapir_archicad_mcp/tools/generated/official/component_commands.py
tapir_archicad_mcp/tools/generated/official/element_geometry_commands.py
tapir_archicad_mcp/tools/generated/official/element_listing_commands.py
tapir_archicad_mcp/tools/generated/official/element_relation_commands.py
tapir_archicad_mcp/tools/generated/official/layout_book_commands.py
tapir_archicad_mcp/tools/generated/official/navigator_tree_commands.py
tapir_archicad_mcp/tools/generated/official/property_commands.py
tapir_archicad_mcp/tools/generated/official/view_map_commands.py
tapir_archicad_mcp/tools/generated/tapir/__init__.py
tapir_archicad_mcp/tools/generated/tapir/application_commands.py
tapir_archicad_mcp/tools/generated/tapir/attribute_commands.py
tapir_archicad_mcp/tools/generated/tapir/element_commands.py
tapir_archicad_mcp/tools/generated/tapir/favorites_commands.py
tapir_archicad_mcp/tools/generated/tapir/issue_management_commands.py
tapir_archicad_mcp/tools/generated/tapir/library_commands.py
tapir_archicad_mcp/tools/generated/tapir/navigator_commands.py
tapir_archicad_mcp/tools/generated/tapir/project_commands.py
tapir_archicad_mcp/tools/generated/tapir/property_commands.py
tapir_archicad_mcp-0.3.1.dist-info/METADATA
tapir_archicad_mcp-0.3.1.dist-info/WHEEL
tapir_archicad_mcp-0.3.1.dist-info/entry_points.txt
tapir_archicad_mcp-0.3.1.dist-info/RECORD
