Metadata-Version: 2.4
Name: tapir-archicad-mcp
Version: 0.3.1
Summary: An MCP server that enables AI agents to automate Archicad using natural language via intelligent, semantic tool discovery.
Project-URL: Homepage, https://github.com/SzamosiMate/tapir-archicad-MCP
Project-URL: Bug Tracker, https://github.com/SzamosiMate/tapir-archicad-MCP/issues
Author-email: SzamosiMate <szamimate@yahoo.com>
License-Expression: MIT
Keywords: ai,api,archicad,automation,bim,llm,mcp
Classifier: Development Status :: 4 - Beta
Classifier: Environment :: Console
Classifier: Intended Audience :: Developers
Classifier: License :: OSI Approved :: MIT License
Classifier: Operating System :: OS Independent
Classifier: Programming Language :: Python :: 3
Classifier: Programming Language :: Python :: 3.12
Classifier: Programming Language :: Python :: 3.13
Classifier: Topic :: Scientific/Engineering
Classifier: Topic :: Software Development :: Libraries :: Python Modules
Requires-Python: >=3.12
Requires-Dist: faiss-cpu>=1.12.0
Requires-Dist: fastmcp>=2.10.5
Requires-Dist: multiconn-archicad>=0.5.1
Requires-Dist: sentence-transformers>=5.1.0
